DESCRIPTION.rst
LICENSE.txt
README.rst
setup.py
dfoalgos/__init__.py
dfoalgos/base.py
dfoalgos/pattern.py
dfoalgos/rankgrad.py
dfoalgos/simplex.py
dfoalgos.egg-info/PKG-INFO
dfoalgos.egg-info/SOURCES.txt
dfoalgos.egg-info/dependency_links.txt
dfoalgos.egg-info/requires.txt
dfoalgos.egg-info/top_level.txt