Metadata-Version: 1.1
Name: dfoalgos
Version: 0.4
Summary: Derivative-free optimization algorithms
Home-page: https://ls11-www.cs.tu-dortmund.de/people/swessing/dfoalgos/doc/
Author: Simon Wessing
Author-email: simon.wessing@tu-dortmund.de
License: BSD
Keywords: derivative-free optimization algorithm simplex Spendley Nelder Mead Kelley pattern search
Platform: UNKNOWN
Classifier: Development Status :: 4 - Beta
Classifier: Intended Audience :: Science/Research
Classifier: Topic :: Scientific/Engineering
Classifier: Topic :: Scientific/Engineering :: Mathematics
Classifier: Topic :: Scientific/Engineering :: Artificial Intelligence
Classifier: License :: OSI Approved :: BSD License
Classifier: Programming Language :: Python :: 2
Classifier: Programming Language :: Python :: 2.7
Classifier: Programming Language :: Python :: 3
Classifier: Programming Language :: Python :: 3.4
Requires: numpy
Requires: optproblems
